eto/__init__.py
eto/config.py
eto/connectors/__init__.py
eto/connectors/base.py
eto/connectors/coco.py
eto/fluent.py
eto/internal/__init__.py
eto/internal/api/__init__.py
eto/internal/api/datasets_api.py
eto/internal/api/jobs_api.py
eto/internal/api_client.py
eto/internal/apis/__init__.py
eto/internal/configuration.py
eto/internal/exceptions.py
eto/internal/model/__init__.py
eto/internal/model/coco_config.py
eto/internal/model/coco_source.py
eto/internal/model/create_job_request.py
eto/internal/model/dataset.py
eto/internal/model/dataset_details.py
eto/internal/model/inline_response200.py
eto/internal/model/inline_response2001.py
eto/internal/model/inline_response404.py
eto/internal/model/job.py
eto/internal/model_utils.py
eto/internal/models/__init__.py
eto/internal/rest.py
eto/resolver.py
eto/spark.py
eto/util.py
etosdk-0.2.dist-info/LICENSE
etosdk-0.2.dist-info/WHEEL
etosdk-0.2.dist-info/METADATA
etosdk-0.2.dist-info/RECORD
