Metadata-Version: 2.1
Name: etosdk
Version: 0.2
Summary: Eto Labs Python SDK
Author: Eto Devs
Author-email: devs@eto.ai
Requires-Python: >=3.9,<4.0
Classifier: Programming Language :: Python :: 3
Classifier: Programming Language :: Python :: 3.10
Classifier: Programming Language :: Python :: 3.9
Requires-Dist: python-dateutil (>=2.8.2,<3.0.0)
Requires-Dist: rikai (>=0.0.14,<0.0.15)
Requires-Dist: urllib3 (>=1.26.7,<2.0.0)
